.gitignore
LICENSE
MANIFEST.in
README.md
cutlet.png
pyproject.toml
pytest.ini
setup.py
.github/FUNDING.yml
.github/workflows/linux.yml
cutlet/__init__.py
cutlet/cli.py
cutlet/cutlet.py
cutlet/exceptions.tsv
cutlet/mapping.py
cutlet.egg-info/PKG-INFO
cutlet.egg-info/SOURCES.txt
cutlet.egg-info/dependency_links.txt
cutlet.egg-info/entry_points.txt
cutlet.egg-info/requires.txt
cutlet.egg-info/top_level.txt
cutlet/test/blns.json
cutlet/test/test_basic.py