Metadata-Version: 2.1
Name: cutlet
Version: 0.1.16
Summary: Romaji converter
Home-page: https://github.com/polm/cutlet
Author: Paul O'Leary McCann
Author-email: polm@dampfkraft.com
License: UNKNOWN
Platform: UNKNOWN
Classifier: License :: OSI Approved :: MIT License
Classifier: Natural Language :: Japanese
Requires-Python: >=3.5
